cbwfq_utils.py
cbwfq_utils-0.1.1.dist-info/METADATA
cbwfq_utils-0.1.1.dist-info/WHEEL
cbwfq_utils-0.1.1.dist-info/RECORD
