Metadata-Version: 2.3
Name: cbwfq-utils
Version: 0.1.1
Summary: CBWFQ calculation utilities
Keywords: cbwfq,qos,networking
Author: Yaroslav WWFyb3NsYXYg
Author-email: minestrim13@gmail.com
Requires-Python: >=3.11,<4.0
Classifier: Programming Language :: Python :: 3
Classifier: Programming Language :: Python :: 3.11
Classifier: Programming Language :: Python :: 3.12
Classifier: Programming Language :: Python :: 3.13
Requires-Dist: numpy (>=2.2,<3.0)
Requires-Dist: scipy (>=1.15,<2.0)
